setup.cfg
setup.py
ibmm2gv/__init__.py
ibmm2gv/main.py
ibmm2gv.egg-info/PKG-INFO
ibmm2gv.egg-info/SOURCES.txt
ibmm2gv.egg-info/dependency_links.txt
ibmm2gv.egg-info/entry_points.txt
ibmm2gv.egg-info/not-zip-safe
ibmm2gv.egg-info/requires.txt
ibmm2gv.egg-info/top_level.txt
tests/render-season-zh.bat
tests/render-season-zh.sh
tests/render-season.bat
tests/render-season.sh
tests/season-zh.ibmm
tests/season.ibmm