Metadata-Version: 1.0
Name: ibmm2gv
Version: 0.0.1
Summary: indentation-based mind map in Python, render by graphviz.
Home-page: http://code.google.com/p/ibmm
Author: LaiYonghao
Author-email: mail@laiyonghao.com
License: mit
Keywords: mind map,graphviz
Platform: UNKNOWN
